pureluks/__init__.py
pureluks/pureluks.py
pureluks-0.0.2.dist-info/METADATA
pureluks-0.0.2.dist-info/WHEEL
pureluks-0.0.2.dist-info/licenses/LICENSE
pureluks-0.0.2.dist-info/RECORD
