Metadata-Version: 2.1
Name: pureluks
Version: 0.0.2
Summary: Simple cryptsetup wrapper for LUKS image files
Project-URL: Homepage, https://github.com/4ndrs/pureluks
Project-URL: Bug Tracker, https://github.com/4ndrs/pureluks/issues
Author-email: 4ndrs <andres.degozaru@gmail.com>
License: MIT License
Classifier: License :: OSI Approved :: MIT License
Classifier: Operating System :: POSIX :: Linux
Classifier: Programming Language :: Python :: 3
Classifier: Topic :: Software Development :: Libraries :: Python Modules
Requires-Python: >=3.10
